{
  "kind": "quant_signals",
  "generated_at": "2026-04-25T15:25:52+00:00",
  "snapshot_count": 11,
  "errors": [
    "arbitrum:0xf6dae0d2be4993b00a2673360820af6bafd53887: 'NoneType' object is not iterable"
  ],
  "filters": {
    "scan_chains": [
      "arbitrum",
      "bnb",
      "avalanche"
    ],
    "binance_usdt_only": false,
    "binance_symbol_count": 0,
    "binance_min_liquidity_usd": 5000.0,
    "binance_source": "disabled",
    "matched_signal_count": 11
  },
  "signals": [
    {
      "snapshot_id": 497,
      "ts": "2026-04-25T15:25:44+00:00",
      "chain": "arbitrum",
      "address": "0x6eb5c25ef5dd5c182fb4e009dfcd589319dd3996",
      "symbol": "ABTXYZ",
      "binance_usdt_futures": false,
      "binance_symbol": "",
      "binance_base_asset": "",
      "binance_match_type": "",
      "pump_score": 27.55,
      "dump_score": 6.25,
      "anomaly_score": 48.08,
      "smart_money_score": 0.0,
      "risk_score": 25.0,
      "label": "watch",
      "reasons": [
        "risk:freeze_authority"
      ],
      "metrics": {
        "price": 0.01021,
        "liquidity_usd": 271849.46,
        "price_change_1h_pct": 18.68,
        "derived_price_change_pct": 0.0,
        "volume_1h_usd": 11169.45,
        "hourly_volume_ratio": 2.436437107870003,
        "buy_imbalance": 0.0,
        "whale_net_usd": 0.0,
        "liquidity_change_pct": 0.0,
        "top_trader_pnl_usd": 0
      }
    },
    {
      "snapshot_id": 493,
      "ts": "2026-04-25T15:25:44+00:00",
      "chain": "arbitrum",
      "address": "0x6985884c4392d348587b19cb9eaaf157f13271cd",
      "symbol": "ZRO",
      "binance_usdt_futures": false,
      "binance_symbol": "",
      "binance_base_asset": "",
      "binance_match_type": "",
      "pump_score": 0.0,
      "dump_score": 6.57,
      "anomaly_score": 11.22,
      "smart_money_score": 0.0,
      "risk_score": 25.0,
      "label": "watch",
      "reasons": [
        "risk:freeze_authority"
      ],
      "metrics": {
        "price": 1.57,
        "liquidity_usd": 182628.33,
        "price_change_1h_pct": -0.35,
        "derived_price_change_pct": -0.6329113924050638,
        "volume_1h_usd": 955.39,
        "hourly_volume_ratio": 0.782260711266438,
        "buy_imbalance": 0.0,
        "whale_net_usd": 0.0,
        "liquidity_change_pct": 5.263833476084147,
        "top_trader_pnl_usd": 0
      }
    },
    {
      "snapshot_id": 488,
      "ts": "2026-04-25T15:25:44+00:00",
      "chain": "arbitrum",
      "address": "0x7f9fbf9bdd3f4105c478b996b648fe6e828a1e98",
      "symbol": "APE",
      "binance_usdt_futures": false,
      "binance_symbol": "",
      "binance_base_asset": "",
      "binance_match_type": "",
      "pump_score": 0.0,
      "dump_score": 9.57,
      "anomaly_score": 6.74,
      "smart_money_score": 0.0,
      "risk_score": 25.0,
      "label": "watch",
      "reasons": [
        "risk:freeze_authority"
      ],
      "metrics": {
        "price": 0.1598,
        "liquidity_usd": 118231.0,
        "price_change_1h_pct": 1.44,
        "derived_price_change_pct": -9.101251422070542,
        "volume_1h_usd": 2372.76,
        "hourly_volume_ratio": 0.1565298835002679,
        "buy_imbalance": 0.0,
        "whale_net_usd": 0.0,
        "liquidity_change_pct": -4.736397293643803,
        "top_trader_pnl_usd": 0
      }
    },
    {
      "snapshot_id": 496,
      "ts": "2026-04-25T15:25:44+00:00",
      "chain": "arbitrum",
      "address": "0x4186bfc76e2e237523cbc30fd220fe055156b41f",
      "symbol": "rsETH",
      "binance_usdt_futures": false,
      "binance_symbol": "",
      "binance_base_asset": "",
      "binance_match_type": "",
      "pump_score": 0.0,
      "dump_score": 9.25,
      "anomaly_score": 0.0,
      "smart_money_score": 0.0,
      "risk_score": 37.0,
      "label": "watch",
      "reasons": [
        "risk:freeze_authority",
        "risk:thin_liquidity"
      ],
      "metrics": {
        "price": 1159.98,
        "liquidity_usd": 232.93,
        "price_change_1h_pct": 0.0,
        "derived_price_change_pct": 0.0,
        "volume_1h_usd": 0.0,
        "hourly_volume_ratio": 0.0,
        "buy_imbalance": 0.0,
        "whale_net_usd": 0.0,
        "liquidity_change_pct": 0.0,
        "top_trader_pnl_usd": 0
      }
    },
    {
      "snapshot_id": 498,
      "ts": "2026-04-25T15:25:44+00:00",
      "chain": "arbitrum",
      "address": "0xbdf8c7b8371557b78428032a54965fc52ad98685",
      "symbol": "ORMBLG",
      "binance_usdt_futures": false,
      "binance_symbol": "",
      "binance_base_asset": "",
      "binance_match_type": "",
      "pump_score": 0.0,
      "dump_score": 9.25,
      "anomaly_score": 0.0,
      "smart_money_score": 0.0,
      "risk_score": 37.0,
      "label": "watch",
      "reasons": [
        "risk:freeze_authority",
        "risk:thin_liquidity"
      ],
      "metrics": {
        "price": 5.212e-06,
        "liquidity_usd": 750.3,
        "price_change_1h_pct": 0.0,
        "derived_price_change_pct": 0.0,
        "volume_1h_usd": 0.0,
        "hourly_volume_ratio": 0.0,
        "buy_imbalance": 0.0,
        "whale_net_usd": 0.0,
        "liquidity_change_pct": 0.0,
        "top_trader_pnl_usd": 0
      }
    },
    {
      "snapshot_id": 490,
      "ts": "2026-04-25T15:25:44+00:00",
      "chain": "arbitrum",
      "address": "0x0c1c1c109fe34733fca54b82d7b46b75cfb71f6e",
      "symbol": "CHIP",
      "binance_usdt_futures": false,
      "binance_symbol": "",
      "binance_base_asset": "",
      "binance_match_type": "",
      "pump_score": 0.0,
      "dump_score": 7.79,
      "anomaly_score": 8.85,
      "smart_money_score": 0.0,
      "risk_score": 25.0,
      "label": "watch",
      "reasons": [
        "risk:freeze_authority"
      ],
      "metrics": {
        "price": 0.07156,
        "liquidity_usd": 1160737.69,
        "price_change_1h_pct": -0.97,
        "derived_price_change_pct": -8.81753312945973,
        "volume_1h_usd": 33034.69,
        "hourly_volume_ratio": 0.7583350057529897,
        "buy_imbalance": 0.0,
        "whale_net_usd": 0.0,
        "liquidity_change_pct": -0.9491074828996166,
        "top_trader_pnl_usd": 0
      }
    },
    {
      "snapshot_id": 489,
      "ts": "2026-04-25T15:25:44+00:00",
      "chain": "arbitrum",
      "address": "0x912ce59144191c1204e64559fe8253a0e49e6548",
      "symbol": "ARB",
      "binance_usdt_futures": false,
      "binance_symbol": "",
      "binance_base_asset": "",
      "binance_match_type": "",
      "pump_score": 0.0,
      "dump_score": 6.89,
      "anomaly_score": 2.34,
      "smart_money_score": 0.0,
      "risk_score": 25.0,
      "label": "watch",
      "reasons": [
        "risk:freeze_authority"
      ],
      "metrics": {
        "price": 0.1298,
        "liquidity_usd": 4063999.39,
        "price_change_1h_pct": -0.06,
        "derived_price_change_pct": -1.4426727410782176,
        "volume_1h_usd": 3531.46,
        "hourly_volume_ratio": 0.1862028611273771,
        "buy_imbalance": 0.0,
        "whale_net_usd": 0.0,
        "liquidity_change_pct": -0.8316073784535656,
        "top_trader_pnl_usd": 0
      }
    },
    {
      "snapshot_id": 491,
      "ts": "2026-04-25T15:25:44+00:00",
      "chain": "arbitrum",
      "address": "0x2f2a2543b76a4166549f7aab2e75bef0aefc5b0f",
      "symbol": "WBTC",
      "binance_usdt_futures": false,
      "binance_symbol": "",
      "binance_base_asset": "",
      "binance_match_type": "",
      "pump_score": 0.0,
      "dump_score": 6.59,
      "anomaly_score": 0.67,
      "smart_money_score": 0.0,
      "risk_score": 25.0,
      "label": "watch",
      "reasons": [
        "risk:freeze_authority"
      ],
      "metrics": {
        "price": 77402.34,
        "liquidity_usd": 48291529.05,
        "price_change_1h_pct": 0.04,
        "derived_price_change_pct": -0.07255494358659109,
        "volume_1h_usd": 9088.1,
        "hourly_volume_ratio": 0.030221092475982658,
        "buy_imbalance": 0.0,
        "whale_net_usd": 0.0,
        "liquidity_change_pct": -0.4849614679368881,
        "top_trader_pnl_usd": 0
      }
    },
    {
      "snapshot_id": 495,
      "ts": "2026-04-25T15:25:44+00:00",
      "chain": "arbitrum",
      "address": "0x82af49447d8a07e3bd95bd0d56f35241523fbab1",
      "symbol": "WETH",
      "binance_usdt_futures": false,
      "binance_symbol": "",
      "binance_base_asset": "",
      "binance_match_type": "",
      "pump_score": 0.0,
      "dump_score": 6.48,
      "anomaly_score": 2.73,
      "smart_money_score": 0.0,
      "risk_score": 25.0,
      "label": "watch",
      "reasons": [
        "risk:freeze_authority"
      ],
      "metrics": {
        "price": 2317.087,
        "liquidity_usd": 12430556.96,
        "price_change_1h_pct": 0.03,
        "derived_price_change_pct": -0.17095674165411193,
        "volume_1h_usd": 41526.1,
        "hourly_volume_ratio": 0.27305601772534294,
        "buy_imbalance": 0.0,
        "whale_net_usd": 0.0,
        "liquidity_change_pct": -0.3272774390088171,
        "top_trader_pnl_usd": 0
      }
    },
    {
      "snapshot_id": 494,
      "ts": "2026-04-25T15:25:44+00:00",
      "chain": "arbitrum",
      "address": "0xaf88d065e77c8cc2239327c5edb3a432268e5831",
      "symbol": "USDC",
      "binance_usdt_futures": false,
      "binance_symbol": "",
      "binance_base_asset": "",
      "binance_match_type": "",
      "pump_score": 0.0,
      "dump_score": 6.44,
      "anomaly_score": 2.72,
      "smart_money_score": 0.0,
      "risk_score": 25.0,
      "label": "watch",
      "reasons": [
        "risk:freeze_authority"
      ],
      "metrics": {
        "price": 0.9996,
        "liquidity_usd": 55541268.91,
        "price_change_1h_pct": 0.0,
        "derived_price_change_pct": 0.0,
        "volume_1h_usd": 263204.45,
        "hourly_volume_ratio": 0.28153526331294215,
        "buy_imbalance": 0.0,
        "whale_net_usd": 0.0,
        "liquidity_change_pct": -0.2688249328648278,
        "top_trader_pnl_usd": 0
      }
    },
    {
      "snapshot_id": 492,
      "ts": "2026-04-25T15:25:44+00:00",
      "chain": "arbitrum",
      "address": "0xe50fa9b3c56ffb159cb0fca61f5c9d750e8128c8",
      "symbol": "aArbWETH",
      "binance_usdt_futures": false,
      "binance_symbol": "",
      "binance_base_asset": "",
      "binance_match_type": "",
      "pump_score": 0.0,
      "dump_score": 6.26,
      "anomaly_score": 5.52,
      "smart_money_score": 0.0,
      "risk_score": 25.0,
      "label": "watch",
      "reasons": [
        "risk:freeze_authority"
      ],
      "metrics": {
        "price": 2305.65,
        "liquidity_usd": 2294793.67,
        "price_change_1h_pct": -0.01,
        "derived_price_change_pct": 0.29405495695749767,
        "volume_1h_usd": 19876.09,
        "hourly_volume_ratio": 0.22514636755602976,
        "buy_imbalance": 0.0,
        "whale_net_usd": 0.0,
        "liquidity_change_pct": 4.968618262402573,
        "top_trader_pnl_usd": 0
      }
    }
  ]
}