{
  "kind": "quant_outcomes",
  "generated_at": "2026-04-25T07:55:18+00:00",
  "evaluated_count": 4,
  "hit_count": 0,
  "hit_rate": 0.0,
  "outcomes": [
    {
      "snapshot_id": 363,
      "horizon_min": 60,
      "target_pct": 10.0,
      "evaluated_ts": "2026-04-25T07:55:18+00:00",
      "chain": "ethereum",
      "address": "0x66df1964d55f3ee29654fe0d23ee269118d5ea13",
      "symbol": "FAFIFU",
      "label": "anomaly_watch",
      "predicted_direction": "up",
      "entry_price": 2.317e-05,
      "current_price": 2.317e-05,
      "return_pct": 0.0,
      "is_true": false,
      "reasons": [
        "predicted_up",
        "return_0.00pct",
        "target_10.00pct",
        "label_anomaly_watch",
        "not_confirmed"
      ]
    },
    {
      "snapshot_id": 362,
      "horizon_min": 60,
      "target_pct": 10.0,
      "evaluated_ts": "2026-04-25T07:55:18+00:00",
      "chain": "ethereum",
      "address": "0x411c794c65b3fccfb6f32e2f9daead960e297507",
      "symbol": "fukuyama",
      "label": "anomaly_watch",
      "predicted_direction": "down",
      "entry_price": 4.425e-10,
      "current_price": 4.425e-10,
      "return_pct": 0.0,
      "is_true": false,
      "reasons": [
        "predicted_down",
        "return_0.00pct",
        "target_10.00pct",
        "label_anomaly_watch",
        "not_confirmed"
      ]
    },
    {
      "snapshot_id": 358,
      "horizon_min": 60,
      "target_pct": 10.0,
      "evaluated_ts": "2026-04-25T07:55:18+00:00",
      "chain": "ethereum",
      "address": "0xb268104d863b31ec2700b9df0b2aaa93bd5b98b8",
      "symbol": "FAFIFU",
      "label": "anomaly_watch",
      "predicted_direction": "down",
      "entry_price": 1.222e-08,
      "current_price": 1.222e-08,
      "return_pct": 0.0,
      "is_true": false,
      "reasons": [
        "predicted_down",
        "return_0.00pct",
        "target_10.00pct",
        "label_anomaly_watch",
        "not_confirmed"
      ]
    },
    {
      "snapshot_id": 348,
      "horizon_min": 60,
      "target_pct": 10.0,
      "evaluated_ts": "2026-04-25T07:55:18+00:00",
      "chain": "ethereum",
      "address": "0xaff2565091e7207191dbe340b8528d02fa78d044",
      "symbol": "ASTEROID",
      "label": "anomaly_watch",
      "predicted_direction": "up",
      "entry_price": 0.01184,
      "current_price": 0.01088,
      "return_pct": -8.1081,
      "is_true": false,
      "reasons": [
        "predicted_up",
        "return_-8.11pct",
        "target_10.00pct",
        "label_anomaly_watch",
        "not_confirmed"
      ]
    }
  ]
}