{
  "kind": "quant_outcomes",
  "generated_at": "2026-04-26T16:19:59+00:00",
  "evaluated_count": 4,
  "hit_count": 2,
  "hit_rate": 0.5,
  "outcomes": [
    {
      "snapshot_id": 730,
      "horizon_min": 60,
      "target_pct": 10.0,
      "evaluated_ts": "2026-04-26T16:19:58+00:00",
      "chain": "arbitrum",
      "address": "0xdc6576e635f9a5ea134a069b74aebe3cdc0d548b",
      "symbol": "MEKA",
      "label": "watch",
      "predicted_direction": "up",
      "entry_price": 0.04364,
      "current_price": 0.08129,
      "return_pct": 86.2741,
      "is_true": true,
      "reasons": [
        "predicted_up",
        "return_86.27pct",
        "target_10.00pct",
        "label_watch",
        "pump_confirmed"
      ]
    },
    {
      "snapshot_id": 729,
      "horizon_min": 60,
      "target_pct": 10.0,
      "evaluated_ts": "2026-04-26T16:19:58+00:00",
      "chain": "arbitrum",
      "address": "0xb36edc1cb45d9e9383ff0235e1a502a5421d37b6",
      "symbol": "MNFLAB",
      "label": "watch",
      "predicted_direction": "up",
      "entry_price": 0.0006765,
      "current_price": 0.002512,
      "return_pct": 271.323,
      "is_true": true,
      "reasons": [
        "predicted_up",
        "return_271.32pct",
        "target_10.00pct",
        "label_watch",
        "pump_confirmed"
      ]
    },
    {
      "snapshot_id": 724,
      "horizon_min": 60,
      "target_pct": 10.0,
      "evaluated_ts": "2026-04-26T16:19:58+00:00",
      "chain": "arbitrum",
      "address": "0x912ce59144191c1204e64559fe8253a0e49e6548",
      "symbol": "ARB",
      "label": "watch",
      "predicted_direction": "down",
      "entry_price": 0.1303,
      "current_price": 0.1306,
      "return_pct": 0.2302,
      "is_true": false,
      "reasons": [
        "predicted_down",
        "return_0.23pct",
        "target_10.00pct",
        "label_watch",
        "not_confirmed"
      ]
    },
    {
      "snapshot_id": 722,
      "horizon_min": 60,
      "target_pct": 10.0,
      "evaluated_ts": "2026-04-26T16:19:58+00:00",
      "chain": "arbitrum",
      "address": "0x2f2a2543b76a4166549f7aab2e75bef0aefc5b0f",
      "symbol": "WBTC",
      "label": "dump_risk",
      "predicted_direction": "down",
      "entry_price": 77663.062,
      "current_price": 77801.64,
      "return_pct": 0.1784,
      "is_true": false,
      "reasons": [
        "predicted_down",
        "return_0.18pct",
        "target_10.00pct",
        "label_dump_risk",
        "not_confirmed"
      ]
    }
  ]
}