{
  "kind": "quant_signals",
  "generated_at": "2026-05-01T17:13:33+00:00",
  "snapshot_count": 29,
  "errors": [],
  "filters": {
    "scan_chains": [
      "solana",
      "ethereum",
      "base"
    ],
    "trade_limit": 35,
    "top_trader_limit": 5,
    "smart_money_enabled": true,
    "binance_usdt_only": false,
    "binance_symbol_count": 0,
    "binance_min_liquidity_usd": 5000.0,
    "binance_source": "disabled",
    "matched_signal_count": 29
  },
  "signals": [
    {
      "snapshot_id": 450,
      "ts": "2026-05-01T17:12:10+00:00",
      "chain": "solana",
      "address": "3nyFwxJsiDDoDzHrPDxY64XdE5NVxfVKfcSDmdfEZxBT",
      "symbol": "POKEDAQ",
      "binance_usdt_futures": false,
      "binance_symbol": "",
      "binance_base_asset": "",
      "binance_match_type": "",
      "pump_score": 25.85,
      "dump_score": 3.0,
      "anomaly_score": 100.0,
      "smart_money_score": 0.0,
      "risk_score": 12.0,
      "label": "anomaly_watch",
      "reasons": [
        "risk:thin_liquidity",
        "ml_isolation_forest_anomaly"
      ],
      "metrics": {
        "price": 5.047e-05,
        "liquidity_usd": 1840.47,
        "price_change_1h_pct": 0.06,
        "derived_price_change_pct": 0.0,
        "volume_1h_usd": 0.36,
        "hourly_volume_ratio": 24.0,
        "buy_imbalance": 0.0,
        "whale_net_usd": 0.0,
        "liquidity_change_pct": 0.0,
        "top_trader_pnl_usd": 0
      }
    },
    {
      "snapshot_id": 457,
      "ts": "2026-05-01T17:12:10+00:00",
      "chain": "solana",
      "address": "E1aDUPSZYknvqVg8sKfH2Aa5BH96zXmwR9isPtksQi6u",
      "symbol": "BURNIE",
      "binance_usdt_futures": false,
      "binance_symbol": "",
      "binance_base_asset": "",
      "binance_match_type": "",
      "pump_score": 66.0,
      "dump_score": 0.0,
      "anomaly_score": 96.6,
      "smart_money_score": 0.0,
      "risk_score": 0.0,
      "label": "anomaly_watch",
      "reasons": [
        "sudden_rise_price_plus_volume",
        "ml_isolation_forest_anomaly"
      ],
      "metrics": {
        "price": 0.3371,
        "liquidity_usd": 23809.57,
        "price_change_1h_pct": 164125.0,
        "derived_price_change_pct": 0.0,
        "volume_1h_usd": 12376.39,
        "hourly_volume_ratio": 24.0,
        "buy_imbalance": 0.0,
        "whale_net_usd": 0.0,
        "liquidity_change_pct": 0.0,
        "top_trader_pnl_usd": 0
      }
    },
    {
      "snapshot_id": 455,
      "ts": "2026-05-01T17:12:10+00:00",
      "chain": "solana",
      "address": "Fp4uy42aN5vfk6BhmAvqb1xnonU3MPYaGQw7z55cRUSA",
      "symbol": "USCR",
      "binance_usdt_futures": false,
      "binance_symbol": "",
      "binance_base_asset": "",
      "binance_match_type": "",
      "pump_score": 0.0,
      "dump_score": 3.0,
      "anomaly_score": 91.21,
      "smart_money_score": 0.0,
      "risk_score": 12.0,
      "label": "anomaly_watch",
      "reasons": [
        "risk:thin_liquidity",
        "ml_isolation_forest_anomaly"
      ],
      "metrics": {
        "price": 1.685e-05,
        "liquidity_usd": 3.36,
        "price_change_1h_pct": 0.0,
        "derived_price_change_pct": 0.0,
        "volume_1h_usd": 0.0,
        "hourly_volume_ratio": 0.0,
        "buy_imbalance": 0.0,
        "whale_net_usd": 0.0,
        "liquidity_change_pct": 0.0,
        "top_trader_pnl_usd": 0
      }
    },
    {
      "snapshot_id": 445,
      "ts": "2026-05-01T17:12:10+00:00",
      "chain": "solana",
      "address": "HDmojpFZvf1F421Gev2hh2p1ThaVbWsW5qh9C5Bipump",
      "symbol": "MSPAINTIFY",
      "binance_usdt_futures": false,
      "binance_symbol": "",
      "binance_base_asset": "",
      "binance_match_type": "",
      "pump_score": 43.57,
      "dump_score": 0.0,
      "anomaly_score": 80.15,
      "smart_money_score": 0.0,
      "risk_score": 0.0,
      "label": "anomaly_watch",
      "reasons": [
        "normal_watch",
        "ml_isolation_forest_anomaly"
      ],
      "metrics": {
        "price": 0.0003262,
        "liquidity_usd": 55705.06,
        "price_change_1h_pct": 132.0,
        "derived_price_change_pct": 129.23401264933244,
        "volume_1h_usd": 158513.76,
        "hourly_volume_ratio": 0.9464846864644936,
        "buy_imbalance": 0.0,
        "whale_net_usd": 0.0,
        "liquidity_change_pct": 52.11744912652374,
        "top_trader_pnl_usd": 0
      }
    },
    {
      "snapshot_id": 454,
      "ts": "2026-05-01T17:12:10+00:00",
      "chain": "solana",
      "address": "65FWdgdzbqNB4RAY6gH55xfmW19wtkMmWhALfKw1pump",
      "symbol": "SOL",
      "binance_usdt_futures": false,
      "binance_symbol": "",
      "binance_base_asset": "",
      "binance_match_type": "",
      "pump_score": 66.0,
      "dump_score": 0.0,
      "anomaly_score": 65.0,
      "smart_money_score": 0.0,
      "risk_score": 0.0,
      "label": "watch",
      "reasons": [
        "sudden_rise_price_plus_volume"
      ],
      "metrics": {
        "price": 7.25e-06,
        "liquidity_usd": 0.0,
        "price_change_1h_pct": 206.0,
        "derived_price_change_pct": 0.0,
        "volume_1h_usd": 5103.1,
        "hourly_volume_ratio": 24.0,
        "buy_imbalance": 0.0,
        "whale_net_usd": 0.0,
        "liquidity_change_pct": 0.0,
        "top_trader_pnl_usd": 0
      }
    },
    {
      "snapshot_id": 456,
      "ts": "2026-05-01T17:12:10+00:00",
      "chain": "solana",
      "address": "7DtCjvj1aAj1CuFG2CZGmnCrZCUeA41WC3JCCRbppump",
      "symbol": "Pump",
      "binance_usdt_futures": false,
      "binance_symbol": "",
      "binance_base_asset": "",
      "binance_match_type": "",
      "pump_score": 66.0,
      "dump_score": 0.0,
      "anomaly_score": 65.0,
      "smart_money_score": 0.0,
      "risk_score": 0.0,
      "label": "watch",
      "reasons": [
        "sudden_rise_price_plus_volume"
      ],
      "metrics": {
        "price": 7.955e-06,
        "liquidity_usd": 0.0,
        "price_change_1h_pct": 233.0,
        "derived_price_change_pct": 0.0,
        "volume_1h_usd": 142.29,
        "hourly_volume_ratio": 24.0,
        "buy_imbalance": 0.0,
        "whale_net_usd": 0.0,
        "liquidity_change_pct": 0.0,
        "top_trader_pnl_usd": 0
      }
    },
    {
      "snapshot_id": 447,
      "ts": "2026-05-01T17:12:10+00:00",
      "chain": "solana",
      "address": "CzHc1ugMNhim5JCJC8ebbp4k14jfrbZx1HNcMyEppump",
      "symbol": "MUSK",
      "binance_usdt_futures": false,
      "binance_symbol": "",
      "binance_base_asset": "",
      "binance_match_type": "",
      "pump_score": 36.99,
      "dump_score": 0.0,
      "anomaly_score": 54.09,
      "smart_money_score": 0.0,
      "risk_score": 0.0,
      "label": "watch",
      "reasons": [
        "normal_watch"
      ],
      "metrics": {
        "price": 0.0001605,
        "liquidity_usd": 60353.87,
        "price_change_1h_pct": 30.72,
        "derived_price_change_pct": 26.4775413711584,
        "volume_1h_usd": 22732.28,
        "hourly_volume_ratio": 1.1680561241005807,
        "buy_imbalance": 0.0,
        "whale_net_usd": 0.0,
        "liquidity_change_pct": 12.251852827263379,
        "top_trader_pnl_usd": 0
      }
    },
    {
      "snapshot_id": 439,
      "ts": "2026-05-01T17:12:10+00:00",
      "chain": "solana",
      "address": "8c3JdTcEqy9XdUJ36NAns7XVDfh356nWxvwcMYKNpump",
      "symbol": "Scribbli",
      "binance_usdt_futures": false,
      "binance_symbol": "",
      "binance_base_asset": "",
      "binance_match_type": "",
      "pump_score": 30.53,
      "dump_score": 10.83,
      "anomaly_score": 53.7,
      "smart_money_score": 0.0,
      "risk_score": 0.0,
      "label": "watch",
      "reasons": [
        "normal_watch"
      ],
      "metrics": {
        "price": 0.001255,
        "liquidity_usd": 103991.66,
        "price_change_1h_pct": 13.41,
        "derived_price_change_pct": 16.961789375582487,
        "volume_1h_usd": 538044.33,
        "hourly_volume_ratio": 2.3079874897866963,
        "buy_imbalance": -0.3093793641209069,
        "whale_net_usd": 0.0,
        "liquidity_change_pct": 9.171269024619255,
        "top_trader_pnl_usd": 0
      }
    },
    {
      "snapshot_id": 441,
      "ts": "2026-05-01T17:12:10+00:00",
      "chain": "solana",
      "address": "F8ZVdDU2EdqYaBuJsA488Hr1QPachasWnQF6k3TDpump",
      "symbol": "CCP",
      "binance_usdt_futures": false,
      "binance_symbol": "",
      "binance_base_asset": "",
      "binance_match_type": "",
      "pump_score": 3.27,
      "dump_score": 21.15,
      "anomaly_score": 53.01,
      "smart_money_score": 0.0,
      "risk_score": 0.0,
      "label": "watch",
      "reasons": [
        "normal_watch"
      ],
      "metrics": {
        "price": 0.0007148,
        "liquidity_usd": 69470.47,
        "price_change_1h_pct": -4.4,
        "derived_price_change_pct": -4.2721307084505105,
        "volume_1h_usd": 30281.82,
        "hourly_volume_ratio": 0.40898462343554437,
        "buy_imbalance": -0.44649829784791306,
        "whale_net_usd": 0.0,
        "liquidity_change_pct": -2.2387828663051623,
        "top_trader_pnl_usd": 0
      }
    },
    {
      "snapshot_id": 452,
      "ts": "2026-05-01T17:12:10+00:00",
      "chain": "solana",
      "address": "9V6A9HB5MR4C5hk2vNzszYiw19FkpFjahcrJebJn28RA",
      "symbol": "GDER",
      "binance_usdt_futures": false,
      "binance_symbol": "",
      "binance_base_asset": "",
      "binance_match_type": "",
      "pump_score": 30.0,
      "dump_score": 3.67,
      "anomaly_score": 44.28,
      "smart_money_score": 0.0,
      "risk_score": 0.0,
      "label": "watch",
      "reasons": [
        "normal_watch"
      ],
      "metrics": {
        "price": 9.825e-05,
        "liquidity_usd": 162864.09,
        "price_change_1h_pct": -4.08,
        "derived_price_change_pct": 0.0,
        "volume_1h_usd": 4658254.83,
        "hourly_volume_ratio": 9.93642742751713,
        "buy_imbalance": 0.0,
        "whale_net_usd": 0.0,
        "liquidity_change_pct": 0.0,
        "top_trader_pnl_usd": 0
      }
    },
    {
      "snapshot_id": 451,
      "ts": "2026-05-01T17:12:10+00:00",
      "chain": "solana",
      "address": "22hMncR1gfjQNaNYUDNPszqYEaEDmjfCTGUPkusDpump",
      "symbol": "LUNC",
      "binance_usdt_futures": false,
      "binance_symbol": "",
      "binance_base_asset": "",
      "binance_match_type": "",
      "pump_score": 30.01,
      "dump_score": 0.0,
      "anomaly_score": 41.3,
      "smart_money_score": 0.0,
      "risk_score": 0.0,
      "label": "watch",
      "reasons": [
        "normal_watch"
      ],
      "metrics": {
        "price": 2.36e-06,
        "liquidity_usd": 0.0,
        "price_change_1h_pct": 0.01,
        "derived_price_change_pct": 0.0,
        "volume_1h_usd": 20.13,
        "hourly_volume_ratio": 24.0,
        "buy_imbalance": 0.0,
        "whale_net_usd": 0.0,
        "liquidity_change_pct": 0.0,
        "top_trader_pnl_usd": 0
      }
    },
    {
      "snapshot_id": 453,
      "ts": "2026-05-01T17:12:10+00:00",
      "chain": "solana",
      "address": "8upTcPDaKJ7YtqNEoUFDn38rdnmPEbd7xRzbzFDgpump",
      "symbol": "J&S",
      "binance_usdt_futures": false,
      "binance_symbol": "",
      "binance_base_asset": "",
      "binance_match_type": "",
      "pump_score": 30.0,
      "dump_score": 4.61,
      "anomaly_score": 37.17,
      "smart_money_score": 0.0,
      "risk_score": 0.0,
      "label": "watch",
      "reasons": [
        "normal_watch"
      ],
      "metrics": {
        "price": 2.351e-06,
        "liquidity_usd": 0.0,
        "price_change_1h_pct": -5.12,
        "derived_price_change_pct": 0.0,
        "volume_1h_usd": 134.55,
        "hourly_volume_ratio": 24.0,
        "buy_imbalance": 0.0,
        "whale_net_usd": 0.0,
        "liquidity_change_pct": 0.0,
        "top_trader_pnl_usd": 0
      }
    },
    {
      "snapshot_id": 440,
      "ts": "2026-05-01T17:12:10+00:00",
      "chain": "solana",
      "address": "2LUZGzSprX6DJQGKGaXvGSYnuf4xHfCuJCeeKHfymoon",
      "symbol": "disbelief",
      "binance_usdt_futures": false,
      "binance_symbol": "",
      "binance_base_asset": "",
      "binance_match_type": "",
      "pump_score": 11.86,
      "dump_score": 9.42,
      "anomaly_score": 34.21,
      "smart_money_score": 5.27,
      "risk_score": 0.0,
      "label": "watch",
      "reasons": [
        "normal_watch"
      ],
      "metrics": {
        "price": 0.0001209,
        "liquidity_usd": 42878.39,
        "price_change_1h_pct": -7.31,
        "derived_price_change_pct": -7.568807339449549,
        "volume_1h_usd": 11655.99,
        "hourly_volume_ratio": 0.32983029048327067,
        "buy_imbalance": 0.2633550317138535,
        "whale_net_usd": 0.0,
        "liquidity_change_pct": -4.054455616135382,
        "top_trader_pnl_usd": 0
      }
    },
    {
      "snapshot_id": 458,
      "ts": "2026-05-01T17:12:10+00:00",
      "chain": "base",
      "address": "0xb695559b26bb2c9703ef1935c37aeae9526bab07",
      "symbol": "MOLT",
      "binance_usdt_futures": false,
      "binance_symbol": "",
      "binance_base_asset": "",
      "binance_match_type": "",
      "pump_score": 25.92,
      "dump_score": 3.1,
      "anomaly_score": 33.18,
      "smart_money_score": 0.0,
      "risk_score": 0.0,
      "label": "watch",
      "reasons": [
        "normal_watch"
      ],
      "metrics": {
        "price": 2.451e-05,
        "liquidity_usd": 1758044.41,
        "price_change_1h_pct": 2.39,
        "derived_price_change_pct": -12.992545260915863,
        "volume_1h_usd": 32108.21,
        "hourly_volume_ratio": 2.970629054899178,
        "buy_imbalance": 0.0,
        "whale_net_usd": 0.0,
        "liquidity_change_pct": -4.423692031035705,
        "top_trader_pnl_usd": 0
      }
    },
    {
      "snapshot_id": 460,
      "ts": "2026-05-01T17:12:10+00:00",
      "chain": "base",
      "address": "0x16332535e2c27da578bc2e82beb09ce9d3c8eb07",
      "symbol": "ClawBank",
      "binance_usdt_futures": false,
      "binance_symbol": "",
      "binance_base_asset": "",
      "binance_match_type": "",
      "pump_score": 17.91,
      "dump_score": 0.0,
      "anomaly_score": 30.98,
      "smart_money_score": 0.0,
      "risk_score": 0.0,
      "label": "watch",
      "reasons": [
        "normal_watch"
      ],
      "metrics": {
        "price": 2.647e-05,
        "liquidity_usd": 945935.73,
        "price_change_1h_pct": 6.77,
        "derived_price_change_pct": 17.64444444444443,
        "volume_1h_usd": 17244.34,
        "hourly_volume_ratio": 1.4767872930628272,
        "buy_imbalance": 0.0,
        "whale_net_usd": 0.0,
        "liquidity_change_pct": 11.723699762242669,
        "top_trader_pnl_usd": 0
      }
    },
    {
      "snapshot_id": 449,
      "ts": "2026-05-01T17:12:10+00:00",
      "chain": "solana",
      "address": "AmttynXoDLdxgWH2qAV6CQqnNgfMecyAKuFhMuPopump",
      "symbol": "SOL",
      "binance_usdt_futures": false,
      "binance_symbol": "",
      "binance_base_asset": "",
      "binance_match_type": "",
      "pump_score": 30.0,
      "dump_score": 0.0,
      "anomaly_score": 30.73,
      "smart_money_score": 0.0,
      "risk_score": 0.0,
      "label": "watch",
      "reasons": [
        "normal_watch"
      ],
      "metrics": {
        "price": 2.671e-06,
        "liquidity_usd": 0.0,
        "price_change_1h_pct": 0.0,
        "derived_price_change_pct": 0.0,
        "volume_1h_usd": 171.12,
        "hourly_volume_ratio": 24.0,
        "buy_imbalance": 0.0,
        "whale_net_usd": 0.0,
        "liquidity_change_pct": 0.0,
        "top_trader_pnl_usd": 0
      }
    },
    {
      "snapshot_id": 461,
      "ts": "2026-05-01T17:12:10+00:00",
      "chain": "base",
      "address": "0xab3f23c2abcb4e12cc8b593c218a7ba64ed17ba3",
      "symbol": "CRED",
      "binance_usdt_futures": false,
      "binance_symbol": "",
      "binance_base_asset": "",
      "binance_match_type": "",
      "pump_score": 16.55,
      "dump_score": 0.0,
      "anomaly_score": 28.81,
      "smart_money_score": 1.77,
      "risk_score": 0.0,
      "label": "watch",
      "reasons": [
        "normal_watch"
      ],
      "metrics": {
        "price": 4.312e-06,
        "liquidity_usd": 253522.46,
        "price_change_1h_pct": 1.26,
        "derived_price_change_pct": 24.804630969609278,
        "volume_1h_usd": 6099.77,
        "hourly_volume_ratio": 1.5394382352829836,
        "buy_imbalance": 0.08862395780140105,
        "whale_net_usd": 0.0,
        "liquidity_change_pct": 14.209893872143633,
        "top_trader_pnl_usd": 0
      }
    },
    {
      "snapshot_id": 462,
      "ts": "2026-05-01T17:12:10+00:00",
      "chain": "base",
      "address": "0xc29832025e7652ef58d15f7fa3e232a2fdfaab07",
      "symbol": "ZOE",
      "binance_usdt_futures": false,
      "binance_symbol": "",
      "binance_base_asset": "",
      "binance_match_type": "",
      "pump_score": 2.26,
      "dump_score": 15.57,
      "anomaly_score": 25.45,
      "smart_money_score": 0.0,
      "risk_score": 0.0,
      "label": "watch",
      "reasons": [
        "normal_watch"
      ],
      "metrics": {
        "price": 3.304e-06,
        "liquidity_usd": 271534.18,
        "price_change_1h_pct": -7.75,
        "derived_price_change_pct": -15.735781688344813,
        "volume_1h_usd": 9599.64,
        "hourly_volume_ratio": 0.2825527751175381,
        "buy_imbalance": 0.0,
        "whale_net_usd": 0.0,
        "liquidity_change_pct": -12.274938831991086,
        "top_trader_pnl_usd": 0
      }
    },
    {
      "snapshot_id": 448,
      "ts": "2026-05-01T17:12:10+00:00",
      "chain": "solana",
      "address": "CGEDT9QZDvvH5GmVkWJH2BXiMJqMJySC9ihWyr7Spump",
      "symbol": "BURNIE",
      "binance_usdt_futures": false,
      "binance_symbol": "",
      "binance_base_asset": "",
      "binance_match_type": "",
      "pump_score": 6.14,
      "dump_score": 8.19,
      "anomaly_score": 19.29,
      "smart_money_score": 0.0,
      "risk_score": 0.0,
      "label": "watch",
      "reasons": [
        "normal_watch"
      ],
      "metrics": {
        "price": 0.01317,
        "liquidity_usd": 544367.83,
        "price_change_1h_pct": -8.38,
        "derived_price_change_pct": -6.46306818181819,
        "volume_1h_usd": 26498.8,
        "hourly_volume_ratio": 0.7676766272149922,
        "buy_imbalance": 0.0,
        "whale_net_usd": 0.0,
        "liquidity_change_pct": -0.9232121711924569,
        "top_trader_pnl_usd": 0
      }
    },
    {
      "snapshot_id": 463,
      "ts": "2026-05-01T17:12:10+00:00",
      "chain": "base",
      "address": "0xcbb7c0000ab88b473b1f5afd9ef808440eed33bf",
      "symbol": "cbBTC",
      "binance_usdt_futures": false,
      "binance_symbol": "",
      "binance_base_asset": "",
      "binance_match_type": "",
      "pump_score": 8.14,
      "dump_score": 0.26,
      "anomaly_score": 17.76,
      "smart_money_score": 0.0,
      "risk_score": 0.0,
      "label": "watch",
      "reasons": [
        "normal_watch"
      ],
      "metrics": {
        "price": 78252.26,
        "liquidity_usd": 23109888.93,
        "price_change_1h_pct": -0.29,
        "derived_price_change_pct": 0.0,
        "volume_1h_usd": 2738871.69,
        "hourly_volume_ratio": 1.0173651423302603,
        "buy_imbalance": 0.0,
        "whale_net_usd": 0.0,
        "liquidity_change_pct": 0.0,
        "top_trader_pnl_usd": 0
      }
    },
    {
      "snapshot_id": 466,
      "ts": "2026-05-01T17:12:10+00:00",
      "chain": "base",
      "address": "0x4200000000000000000000000000000000000006",
      "symbol": "WETH",
      "binance_usdt_futures": false,
      "binance_symbol": "",
      "binance_base_asset": "",
      "binance_match_type": "",
      "pump_score": 4.48,
      "dump_score": 0.09,
      "anomaly_score": 10.56,
      "smart_money_score": 0.0,
      "risk_score": 0.0,
      "label": "watch",
      "reasons": [
        "normal_watch"
      ],
      "metrics": {
        "price": 2305.11,
        "liquidity_usd": 128362517.01,
        "price_change_1h_pct": -0.1,
        "derived_price_change_pct": 0.033849318457000524,
        "volume_1h_usd": 808514.1,
        "hourly_volume_ratio": 0.5596208654252859,
        "buy_imbalance": 0.0,
        "whale_net_usd": 0.0,
        "liquidity_change_pct": 0.4910255427924519,
        "top_trader_pnl_usd": 0
      }
    },
    {
      "snapshot_id": 444,
      "ts": "2026-05-01T17:12:10+00:00",
      "chain": "solana",
      "address": "2p5e3sudKx2LtM8iSefaSszMY9nCiHz6CTEASQ9Xpump",
      "symbol": "Dragon",
      "binance_usdt_futures": false,
      "binance_symbol": "",
      "binance_base_asset": "",
      "binance_match_type": "",
      "pump_score": 3.22,
      "dump_score": 2.76,
      "anomaly_score": 9.19,
      "smart_money_score": 0.0,
      "risk_score": 0.0,
      "label": "watch",
      "reasons": [
        "normal_watch"
      ],
      "metrics": {
        "price": 0.0002153,
        "liquidity_usd": 41184.72,
        "price_change_1h_pct": -3.07,
        "derived_price_change_pct": 3.6092396535129896,
        "volume_1h_usd": 39260.26,
        "hourly_volume_ratio": 0.4021760626737629,
        "buy_imbalance": 0.0,
        "whale_net_usd": 0.0,
        "liquidity_change_pct": 1.8168189623587978,
        "top_trader_pnl_usd": 0
      }
    },
    {
      "snapshot_id": 465,
      "ts": "2026-05-01T17:12:10+00:00",
      "chain": "base",
      "address": "0x8c0d3adcf8ce094e1ae437557ec90a6374dc9bdd",
      "symbol": "OVPP",
      "binance_usdt_futures": false,
      "binance_symbol": "",
      "binance_base_asset": "",
      "binance_match_type": "",
      "pump_score": 6.96,
      "dump_score": 0.7,
      "anomaly_score": 9.0,
      "smart_money_score": 0.14,
      "risk_score": 0.0,
      "label": "watch",
      "reasons": [
        "normal_watch"
      ],
      "metrics": {
        "price": 0.01655,
        "liquidity_usd": 895211.31,
        "price_change_1h_pct": -0.78,
        "derived_price_change_pct": 0.5467800729040085,
        "volume_1h_usd": 19746.12,
        "hourly_volume_ratio": 0.8396422017426991,
        "buy_imbalance": 0.006851451246632769,
        "whale_net_usd": 0.0,
        "liquidity_change_pct": 0.25058185365553043,
        "top_trader_pnl_usd": 0
      }
    },
    {
      "snapshot_id": 442,
      "ts": "2026-05-01T17:12:10+00:00",
      "chain": "solana",
      "address": "2ssMotVbTUfRJev2UnibHzHsoeszPzgwbfsTZPSHpump",
      "symbol": "Wish",
      "binance_usdt_futures": false,
      "binance_symbol": "",
      "binance_base_asset": "",
      "binance_match_type": "",
      "pump_score": 4.13,
      "dump_score": 0.0,
      "anomaly_score": 8.18,
      "smart_money_score": 0.0,
      "risk_score": 0.0,
      "label": "watch",
      "reasons": [
        "normal_watch"
      ],
      "metrics": {
        "price": 0.001843,
        "liquidity_usd": 154153.71,
        "price_change_1h_pct": 1.02,
        "derived_price_change_pct": 9.247184350918799,
        "volume_1h_usd": 91155.23,
        "hourly_volume_ratio": 0.40178642330825676,
        "buy_imbalance": 0.0,
        "whale_net_usd": 0.0,
        "liquidity_change_pct": 4.483250412975096,
        "top_trader_pnl_usd": 0
      }
    },
    {
      "snapshot_id": 464,
      "ts": "2026-05-01T17:12:10+00:00",
      "chain": "base",
      "address": "0xa1f72459dfa10bad200ac160ecd78c6b77a747be",
      "symbol": "CLAWNCH",
      "binance_usdt_futures": false,
      "binance_symbol": "",
      "binance_base_asset": "",
      "binance_match_type": "",
      "pump_score": 5.65,
      "dump_score": 0.66,
      "anomaly_score": 7.67,
      "smart_money_score": 0.0,
      "risk_score": 0.0,
      "label": "watch",
      "reasons": [
        "normal_watch"
      ],
      "metrics": {
        "price": 2.138e-05,
        "liquidity_usd": 1165513.4,
        "price_change_1h_pct": 1.66,
        "derived_price_change_pct": -2.3744292237443,
        "volume_1h_usd": 4792.77,
        "hourly_volume_ratio": 0.5199889263335369,
        "buy_imbalance": 0.0,
        "whale_net_usd": 0.0,
        "liquidity_change_pct": -0.9498624761379597,
        "top_trader_pnl_usd": 0
      }
    },
    {
      "snapshot_id": 467,
      "ts": "2026-05-01T17:12:10+00:00",
      "chain": "base",
      "address": "0xa4a2e2ca3fbfe21aed83471d28b6f65a233c6e00",
      "symbol": "TIBBIR",
      "binance_usdt_futures": false,
      "binance_symbol": "",
      "binance_base_asset": "",
      "binance_match_type": "",
      "pump_score": 5.12,
      "dump_score": 0.43,
      "anomaly_score": 7.04,
      "smart_money_score": 0.0,
      "risk_score": 0.0,
      "label": "watch",
      "reasons": [
        "normal_watch"
      ],
      "metrics": {
        "price": 0.1443,
        "liquidity_usd": 2524377.92,
        "price_change_1h_pct": -0.48,
        "derived_price_change_pct": 0.9797060881735566,
        "volume_1h_usd": 2190.82,
        "hourly_volume_ratio": 0.6404157929103421,
        "buy_imbalance": 0.0,
        "whale_net_usd": 0.0,
        "liquidity_change_pct": 0.8579154644819937,
        "top_trader_pnl_usd": 0
      }
    },
    {
      "snapshot_id": 446,
      "ts": "2026-05-01T17:12:10+00:00",
      "chain": "solana",
      "address": "HrMp2mmpyDZJ65Mspzib7NJPXeZe2cvY5stfHG9nhWTH",
      "symbol": "PUP",
      "binance_usdt_futures": false,
      "binance_symbol": "",
      "binance_base_asset": "",
      "binance_match_type": "",
      "pump_score": 5.21,
      "dump_score": 0.89,
      "anomaly_score": 6.94,
      "smart_money_score": 0.0,
      "risk_score": 0.0,
      "label": "watch",
      "reasons": [
        "normal_watch"
      ],
      "metrics": {
        "price": 0.0007605,
        "liquidity_usd": 85636.71,
        "price_change_1h_pct": 0.46,
        "derived_price_change_pct": -2.2367913613574997,
        "volume_1h_usd": 27400.33,
        "hourly_volume_ratio": 0.5999315341856322,
        "buy_imbalance": 0.0,
        "whale_net_usd": 0.0,
        "liquidity_change_pct": -1.276036650085603,
        "top_trader_pnl_usd": 0
      }
    },
    {
      "snapshot_id": 459,
      "ts": "2026-05-01T17:12:10+00:00",
      "chain": "base",
      "address": "0x5f980dcfc4c0fa3911554cf5ab288ed0eb13dba3",
      "symbol": "GITLAWB",
      "binance_usdt_futures": false,
      "binance_symbol": "",
      "binance_base_asset": "",
      "binance_match_type": "",
      "pump_score": 1.89,
      "dump_score": 2.23,
      "anomaly_score": 6.07,
      "smart_money_score": 0.0,
      "risk_score": 0.0,
      "label": "watch",
      "reasons": [
        "normal_watch"
      ],
      "metrics": {
        "price": 3.96e-05,
        "liquidity_usd": 1215914.17,
        "price_change_1h_pct": -0.17,
        "derived_price_change_pct": -4.255319148936162,
        "volume_1h_usd": 5364.82,
        "hourly_volume_ratio": 0.23579973184297626,
        "buy_imbalance": 0.0,
        "whale_net_usd": 0.0,
        "liquidity_change_pct": -2.963415199791841,
        "top_trader_pnl_usd": 0
      }
    },
    {
      "snapshot_id": 443,
      "ts": "2026-05-01T17:12:10+00:00",
      "chain": "solana",
      "address": "6AVAUKa9uxQpruHZUinFECpXEh1usRVtzQWK8N2wpump",
      "symbol": "SCAM",
      "binance_usdt_futures": false,
      "binance_symbol": "",
      "binance_base_asset": "",
      "binance_match_type": "",
      "pump_score": 2.24,
      "dump_score": 0.33,
      "anomaly_score": 3.0,
      "smart_money_score": 0.0,
      "risk_score": 0.0,
      "label": "watch",
      "reasons": [
        "normal_watch"
      ],
      "metrics": {
        "price": 0.0008657,
        "liquidity_usd": 122176.96,
        "price_change_1h_pct": -0.3,
        "derived_price_change_pct": 0.057790106333790794,
        "volume_1h_usd": 29141.26,
        "hourly_volume_ratio": 0.2802773569495642,
        "buy_imbalance": 0.0,
        "whale_net_usd": 0.0,
        "liquidity_change_pct": -0.08630834338518888,
        "top_trader_pnl_usd": 0
      }
    }
  ]
}